[
    {
        "name": "LibC",
        "make-path": "libc",
        "bin-path": "libc/bin/libc.a",
        "output-path": "/lib/libc.a",
        "postbuild": ["cp libc/bin/libc.a qor-userland/lib/libc.a"]
    },
    {
        "name": "LibArg",
        "make-path": "qor-userland/Libraries/libarg",
        "bin-path": "qor-userland/Libraries/libarg/bin/libarg.a",
        "output-path": "/lib/libarg.a",
        "postbuild": ["cp qor-userland/Libraries/libarg/bin/libarg.a qor-userland/lib/libarg.a"]
    },
    {
        "name": "Shell",
        "make-path": "qor-userland/Internals/shell",
        "bin-path": "qor-userland/Internals/shell/bin/shell",
        "output-path": "/bin/shell"
    },
    {
        "name": "Terminal",
        "make-path": "qor-userland/Internals/term",
        "bin-path": "qor-userland/Internals/term/bin/term",
        "output-path": "/bin/term"
    },
    {
        "name": "Hello",
        "make-path": "qor-userland/Examples/hello",
        "bin-path": "qor-userland/Examples/hello/bin/hello",
        "output-path": "/bin/hello"
    },
    {
        "name": "ls",
        "make-path": "qor-userland/Utils/ls",
        "bin-path": "qor-userland/Utils/ls/bin/ls",
        "output-path": "/bin/ls"
    }
]